Metadata-Version: 2.1
Name: boring-stuff
Version: 1.0.0
Summary: A package that will help Developer's to setup project.
Author: Saurabh Apraj
Author-email: saurabhapraj7@gmail.com
